py_termio/__init__.py
py_termio/_consts.py
py_termio/_read.py
py_termio/consts.py
py_termio/exceptions.py
py_termio/py.typed
py_termio/types.py
py_termio/utils.py
py_termio/_utils/__init__.py
py_termio/_utils/_unix_utils.py
py_termio/_utils/_utils.py
py_termio/_utils/_win_utils.py
py_termio-0.1.0.dist-info/licenses/LICENSE.txt
py_termio-0.1.0.dist-info/METADATA
py_termio-0.1.0.dist-info/WHEEL
py_termio-0.1.0.dist-info/top_level.txt
py_termio-0.1.0.dist-info/RECORD
