Metadata-Version: 2.4
Name: py-termio
Version: 0.1.0
Summary: A cross platform (windows and linux) set of tools for working with the terminal.
Author: Yuki Nagato
License:                    GNU LESSER GENERAL PUBLIC LICENSE
Keywords: terminal,IO,Virtual Terminal Sequences
Classifier: Intended Audience :: Developers
Classifier: Programming Language :: Python :: 3
Classifier: Programming Language :: Python :: 3.10
Classifier: Programming Language :: Python :: 3.11
Classifier: Programming Language :: Python :: 3.12
Classifier: Programming Language :: Python :: 3.13
Requires-Python: >=3.10
License-File: LICENSE.txt
Dynamic: license-file
